{
  "package": "zank.mods.datastructium.mixin.mods",
  "required": true,
  "target": "@env(DEFAULT)",
  "minVersion": "0.8",
  "plugin": "zank.mods.datastructium.mixin.DataStructiumMixinPlugin",
  "compatibilityLevel": "JAVA_8",
  "mixins": [
    "farmersdelight.MixinToolIngredient",
    "jeresources.MixinMobWrapper",
    "kubejs.MixinKubeJSResourcePack",
    "masterfulmachinery.MixinMachineStructureRecipe",
    "masterfulmachinery.MixinMachineStructureRecipeData"
  ],
  "server": [],
  "client": [
    "industrialforegoing.MixinJEICustomPlugin"
  ],
  "injectors": {
    "defaultRequire": 1
  }
}
